zeny_mut/__init__.py
zeny_mut/test.py
zeny_mut-0.0.5.dist-info/LICENCE.txt
zeny_mut-0.0.5.dist-info/METADATA
zeny_mut-0.0.5.dist-info/WHEEL
zeny_mut-0.0.5.dist-info/top_level.txt
zeny_mut-0.0.5.dist-info/RECORD
